<?xml version="1.0" encoding="windows-1252"?>
<!--  This file conforms to the DTD xdc/bld/build.dtd -->
<package name="xconfig_empty" version="" producerId="undefined">
    <units>
    </units>
    <sources>
        <srcFile name="package/cfg/empty_pm4fg.c"/>
    </sources>
    <configscripts>
        <srcFile name="C:/Users/Koona/Documents/MTech/EmbeddedSystems/CCSWorkspace/empty_EK_TM4C123GXL_GNU_TivaTM4C123GH6PM/empty.cfg"/>
    </configscripts>
    <makefiles>
        <srcFile name="package.mak" src="package.bld"/>
        <srcFile name="package/package.xdc.dep" src="package.xdc"/>
        <srcFile name="package/cfg/empty_pm4fg.mak" src="package.bld"/>
        <srcFile name="package/cfg/empty_pm4fg.om4fg.dep" src="package/cfg/empty_pm4fg.c"/>
        <srcFile name="package/cfg/empty_pm4fg.dep" src="package/cfg/empty_pm4fg.cfg"/>
        <srcFile name="package/cfg/empty.xm4fg.mak" src="package.bld"/>
        <srcFile name="package/rel/xconfig_empty.tar.dep" src="package/rel/xconfig_empty.xdc.inc"/>
    </makefiles>
    <targets>
        <target name="gnu.targets.arm.M4F"
            version="gnu.targets.arm.M4F{1,0,4.8,4"
            rawVersion="4.8.4"
            platform="ti.platforms.tiva:LM4F232H5QD"
            isa="v7M4"
            suffix="m4fg"
            rootDir="C:/ti/ccsv6/tools/compiler/gcc-arm-none-eabi-4_8-2014q3"
            os="undefined"
            rts="gnu.targets.arm.rtsv7M">
            <model endian="little"
                codeModel="thumb2"
                dataModel="undefined"/>
        </target>
    </targets>
    <libraries>
    </libraries>
    <configurations>
    <configuration name="empty"
        pname="empty.pm4fg"
        target="gnu.targets.arm.M4F"
        platform="ti.platforms.tiva:TM4C123GH6PM"
        profile="release"
        isPartial="false"
        xCfgScript="package/cfg/empty_pm4fg.cfg"
        xCfgPrefix="package/cfg/empty_pm4fg"
        cfgScript="C:/Users/Koona/Documents/MTech/EmbeddedSystems/CCSWorkspace/empty_EK_TM4C123GXL_GNU_TivaTM4C123GH6PM/empty.cfg"
        cfgArgs="null"
        />
    </configurations>
    <executables>
    <executable name="empty"
        pname="empty.xm4fg"
        target="gnu.targets.arm.M4F"
        platform="ti.platforms.tiva:TM4C123GH6PM"
        profile="release"
        xCfgScript="package/cfg/empty_pm4fg.cfg"
        xCfgPrefix="package/cfg/empty_pm4fg"
        cfgScript="C:/Users/Koona/Documents/MTech/EmbeddedSystems/CCSWorkspace/empty_EK_TM4C123GXL_GNU_TivaTM4C123GH6PM/empty.cfg"
        cfgArgs="null"
        />
    </executables>
    <tests>
    <test exeName="empty.xm4fg"
        args=""
        groupName="empty.xm4fg"
        refOutput="undefined"
        refExitCode="0"
        execArgs=""
        />
    </tests>
    <releases relDir="package/rel/">
    <release name="xconfig_empty"
        pname="xconfig_empty.tar"
        label="default"
    >
        <file name="package/package.bld.xml"/>
        <file name="package/build.cfg"/>
        <file name="package/package.xdc.inc"/>
    </release>
    </releases>
    <repositories>
    </repositories>
</package>
